{"v":"5.7.5","fr":100,"ip":0,"op":100,"w":500,"h":500,"nm":"Avelero Icon","ddd":0,"metadata":{"backgroundColor":{"r":255,"g":255,"b":255}},"assets":[{"id":"0","layers":[{"ddd":0,"ind":1,"ty":4,"nm":"bottomLeft","cl":"primary design","sr":1,"ks":{"p":{"a":0,"k":[28,0],"ix":2},"a":{"a":0,"k":[0,0],"ix":2},"s":{"a":0,"k":[100,100],"ix":2},"r":{"a":0,"k":0,"ix":2},"o":{"a":0,"k":100,"ix":2},"sk":{"a":0,"k":0,"ix":2},"sa":{"a":0,"k":0,"ix":2}},"ao":0,"shapes":[{"ty":"gr","nm":"bottomLeft","it":[{"ty":"sh","d":1,"ks":{"a":0,"k":{"c":true,"v":[[50.405300000000004,222.7197],[0,222.7197],[88.6566,0],[139.0616,0],[50.405300000000004,222.7197],[50.405300000000004,222.7197]],"i":[[0,0],[16.801766666666673,0],[-29.552199999999992,74.2399],[-16.801666666666677,0],[29.552100000000003,-74.2399],[0,0]],"o":[[-16.801766666666666,0],[29.5522,-74.23989999999998],[16.801666666666677,0],[-29.552099999999996,74.23989999999998],[0,0],[0,0]]}}},{"ty":"fl","c":{"a":0,"k":[0,0,0.23921568627450981,1],"ix":4,"x":"var $bm_rt;\n$bm_rt = comp('Avelero Icon').layer('control').effect('primary')('Color');"},"o":{"a":0,"k":100,"ix":5},"r":1,"bm":0,"nm":".primary","mn":"ADBE Vector Graphic - Fill","hd":false,"cl":"primary"},{"ty":"tr","p":{"a":1,"k":[{"t":0,"s":[-142.8788299560547,726.5663452148438],"i":{"x":[0.2],"y":[1]},"o":{"x":[0.4],"y":[0]}},{"t":100,"s":[69.53400421142578,195.83807373046875],"i":{"x":[0.75],"y":[0.75]},"o":{"x":[0.25],"y":[0.25]}}],"ix":2},"a":{"a":0,"k":[69.5308,111.35985],"ix":2},"s":{"a":0,"k":[99.99998807907104,99.99998807907104],"ix":2},"r":{"a":0,"k":0,"ix":2},"o":{"a":0,"k":100,"ix":2},"sk":{"a":0,"k":0,"ix":2},"sa":{"a":0,"k":0,"ix":2}}]}],"ip":0,"op":101,"st":0,"bm":0},{"ddd":0,"ind":2,"ty":4,"nm":"topLeft","cl":"primary design","sr":1,"ks":{"p":{"a":0,"k":[28,0],"ix":2},"a":{"a":0,"k":[0,0],"ix":2},"s":{"a":0,"k":[100,100],"ix":2},"r":{"a":0,"k":0,"ix":2},"o":{"a":0,"k":100,"ix":2},"sk":{"a":0,"k":0,"ix":2},"sa":{"a":0,"k":0,"ix":2}},"ao":0,"shapes":[{"ty":"gr","nm":"topLeft","it":[{"ty":"sh","d":1,"ks":{"a":0,"k":{"c":true,"v":[[50.405300000000004,222.7197],[0,222.7197],[88.6566,0],[139.0616,0],[50.405300000000004,222.7197],[50.405300000000004,222.7197]],"i":[[0,0],[16.801766666666673,0],[-29.552199999999992,74.2399],[-16.801666666666677,0],[29.552100000000003,-74.2399],[0,0]],"o":[[-16.801766666666666,0],[29.5522,-74.23989999999998],[16.801666666666677,0],[-29.552099999999996,74.23989999999998],[0,0],[0,0]]}}},{"ty":"fl","c":{"a":0,"k":[0,0,0.23921568627450981,1],"ix":4,"x":"var $bm_rt;\n$bm_rt = comp('Avelero Icon').layer('control').effect('primary')('Color');"},"o":{"a":0,"k":100,"ix":5},"r":1,"bm":0,"nm":".primary","mn":"ADBE Vector Graphic - Fill","hd":false,"cl":"primary"},{"ty":"tr","p":{"a":1,"k":[{"t":0,"s":[69.53400421142578,195.83807373046875],"i":{"x":[0.2],"y":[1]},"o":{"x":[0.4],"y":[0]}},{"t":100,"s":[312.7024230957031,-411.7369079589844],"i":{"x":[0.75],"y":[0.75]},"o":{"x":[0.25],"y":[0.25]}}],"ix":2},"a":{"a":0,"k":[69.5308,111.35985],"ix":2},"s":{"a":0,"k":[99.99997615814209,99.99997615814209],"ix":2},"r":{"a":0,"k":0,"ix":2},"o":{"a":0,"k":100,"ix":2},"sk":{"a":0,"k":0,"ix":2},"sa":{"a":0,"k":0,"ix":2}}]}],"ip":0,"op":101,"st":0,"bm":0},{"ddd":0,"ind":3,"ty":4,"nm":"topRight","cl":"primary design","sr":1,"ks":{"p":{"a":0,"k":[28,0],"ix":2},"a":{"a":0,"k":[0,0],"ix":2},"s":{"a":0,"k":[100,100],"ix":2},"r":{"a":0,"k":0,"ix":2},"o":{"a":0,"k":100,"ix":2},"sk":{"a":0,"k":0,"ix":2},"sa":{"a":0,"k":0,"ix":2}},"ao":0,"shapes":[{"ty":"gr","nm":"topRight","it":[{"ty":"sh","d":1,"ks":{"a":0,"k":{"c":true,"v":[[50.40599999999998,222.7210610352],[0,222.7210610352],[88.65799999999999,0],[139.062,0],[50.40599999999998,222.7210610352],[50.40599999999998,222.7210610352]],"i":[[0,0],[16.801999999999992,0],[-29.55266666666668,74.24035367840001],[-16.801333333333332,0],[29.55200000000002,-74.2403536784],[0,0]],"o":[[-16.801999999999992,0],[29.552666666666653,-74.2403536784],[16.801333333333332,0],[-29.55200000000002,74.2403536784],[0,0],[0,0]]}}},{"ty":"fl","c":{"a":0,"k":[0,0,0.23921568627450981,1],"ix":4,"x":"var $bm_rt;\n$bm_rt = comp('Avelero Icon').layer('control').effect('primary')('Color');"},"o":{"a":0,"k":100,"ix":5},"r":1,"bm":0,"nm":".primary","mn":"ADBE Vector Graphic - Fill","hd":false,"cl":"primary"},{"ty":"tr","p":{"a":1,"k":[{"t":0,"s":[424.5731506347656,-496.212890625],"i":{"x":[0.2],"y":[1]},"o":{"x":[0.4],"y":[0]}},{"t":100,"s":[181.98919677734375,111.36206817626953],"i":{"x":[0.75],"y":[0.75]},"o":{"x":[0.25],"y":[0.25]}}],"ix":2},"a":{"a":0,"k":[69.531,111.3605305176],"ix":2},"s":{"a":0,"k":[99.99998807907104,99.99998807907104],"ix":2},"r":{"a":0,"k":0,"ix":2},"o":{"a":0,"k":100,"ix":2},"sk":{"a":0,"k":0,"ix":2},"sa":{"a":0,"k":0,"ix":2}}]}],"ip":0,"op":101,"st":0,"bm":0},{"ddd":0,"ind":4,"ty":4,"nm":"bottomRight","cl":"primary design","sr":1,"ks":{"p":{"a":0,"k":[28,0],"ix":2},"a":{"a":0,"k":[0,0],"ix":2},"s":{"a":0,"k":[100,100],"ix":2},"r":{"a":0,"k":0,"ix":2},"o":{"a":0,"k":100,"ix":2},"sk":{"a":0,"k":0,"ix":2},"sa":{"a":0,"k":0,"ix":2}},"ao":0,"shapes":[{"ty":"gr","nm":"bottomRight","it":[{"ty":"sh","d":1,"ks":{"a":0,"k":{"c":true,"v":[[50.40599999999998,222.7210610352],[0,222.7210610352],[88.65799999999999,0],[139.062,0],[50.40599999999998,222.7210610352],[50.40599999999998,222.7210610352]],"i":[[0,0],[16.801999999999992,0],[-29.55266666666668,74.24035367840001],[-16.801333333333332,0],[29.55200000000002,-74.2403536784],[0,0]],"o":[[-16.801999999999992,0],[29.552666666666653,-74.2403536784],[16.801333333333332,0],[-29.55200000000002,74.2403536784],[0,0],[0,0]]}}},{"ty":"fl","c":{"a":0,"k":[0,0,0.23921568627450981,1],"ix":4,"x":"var $bm_rt;\n$bm_rt = comp('Avelero Icon').layer('control').effect('primary')('Color');"},"o":{"a":0,"k":100,"ix":5},"r":1,"bm":0,"nm":".primary","mn":"ADBE Vector Graphic - Fill","hd":false,"cl":"primary"},{"ty":"tr","p":{"a":1,"k":[{"t":0,"s":[181.98919677734375,111.36206817626953],"i":{"x":[0.2],"y":[1]},"o":{"x":[0.4],"y":[0]}},{"t":100,"s":[-60.5947151184082,718.9370727539062],"i":{"x":[0.75],"y":[0.75]},"o":{"x":[0.25],"y":[0.25]}}],"ix":2},"a":{"a":0,"k":[69.531,111.3605305176],"ix":2},"s":{"a":0,"k":[99.99998807907104,99.99998807907104],"ix":2},"r":{"a":0,"k":0,"ix":2},"o":{"a":0,"k":100,"ix":2},"sk":{"a":0,"k":0,"ix":2},"sa":{"a":0,"k":0,"ix":2}}]}],"ip":0,"op":101,"st":0,"bm":0},{"ddd":0,"ind":5,"ty":4,"nm":"SvgClip - box","sr":1,"ks":{"p":{"a":0,"k":[28,0],"ix":2},"a":{"a":0,"k":[0,0],"ix":2},"s":{"a":0,"k":[100,100],"ix":2},"r":{"a":0,"k":0,"ix":2},"o":{"a":0,"k":100,"ix":2},"sk":{"a":0,"k":0,"ix":2},"sa":{"a":0,"k":0,"ix":2}},"ao":0,"shapes":[{"ty":"rc","d":1,"s":{"a":0,"k":[308,308],"ix":2},"p":{"a":0,"k":[126,154],"ix":2},"r":{"a":0,"k":0,"ix":2}},{"ty":"fl","c":{"a":0,"k":[0,0,0],"ix":2},"o":{"a":0,"k":0,"ix":2},"r":1,"bm":0}],"ip":0,"op":101,"st":0,"bm":0}]},{"id":"1","layers":[{"ddd":0,"ind":6,"ty":4,"nm":"SvgClip","sr":1,"ks":{"p":{"a":0,"k":[28,0],"ix":2},"a":{"a":0,"k":[0,0],"ix":2},"s":{"a":0,"k":[100,100],"ix":2},"r":{"a":0,"k":0,"ix":2},"o":{"a":0,"k":100,"ix":2},"sk":{"a":0,"k":0,"ix":2},"sa":{"a":0,"k":0,"ix":2}},"td":1,"ao":0,"shapes":[{"ty":"gr","it":[{"ty":"gr","nm":"Rectangle","it":[{"ty":"rc","d":1,"s":{"a":0,"k":[307.2,307.2],"ix":2},"p":{"a":0,"k":[0,0],"ix":2},"r":{"a":0,"k":0,"ix":2}},{"ty":"fl","c":{"a":0,"k":[0,0,0],"ix":2},"o":{"a":0,"k":100,"ix":2},"r":1,"bm":0},{"ty":"tr","p":{"a":0,"k":[153.60000610351562,153.60000610351562],"ix":2},"a":{"a":0,"k":[0,0],"ix":2},"s":{"a":0,"k":[100,100],"ix":2},"r":{"a":0,"k":0,"ix":2},"o":{"a":0,"k":100,"ix":2},"sk":{"a":0,"k":0,"ix":2},"sa":{"a":0,"k":0,"ix":2}}]},{"ty":"tr","p":{"a":0,"k":[125.76160621643066,153.60006713871553],"ix":2},"a":{"a":0,"k":[153.60000610351562,153.60000610351562],"ix":2},"s":{"a":0,"k":[100,100],"ix":2},"r":{"a":0,"k":0,"ix":2},"o":{"a":0,"k":100,"ix":2},"sk":{"a":0,"k":0,"ix":2},"sa":{"a":0,"k":0,"ix":2}}]}],"ip":0,"op":101,"st":0,"bm":0},{"ddd":0,"refId":"0","w":308,"h":308,"ind":7,"ty":0,"nm":"SVG","sr":1,"ks":{"p":{"a":0,"k":[126,154],"ix":2},"a":{"a":0,"k":[126,154],"ix":2},"s":{"a":0,"k":[100,100],"ix":2},"r":{"a":0,"k":0,"ix":2},"o":{"a":0,"k":100,"ix":2},"sk":{"a":0,"k":0,"ix":2},"sa":{"a":0,"k":0,"ix":2}},"ao":0,"ip":0,"op":101,"st":0,"bm":0,"tt":1}]}],"layers":[{"ddd":0,"ind":1,"ty":3,"nm":"control","sr":1,"ks":{"o":{"a":0,"k":0,"ix":11},"r":{"a":0,"k":0,"ix":10},"p":{"a":0,"k":[0,0,0],"ix":2,"l":2},"a":{"a":0,"k":[0,0,0],"ix":1,"l":2},"s":{"a":0,"k":[100,100,100],"ix":6,"l":2}},"ao":0,"ef":[{"ty":5,"nm":"primary","np":3,"mn":"ADBE Color Control","ix":1,"en":1,"ef":[{"ty":2,"nm":"Color","mn":"ADBE Color Control-0001","ix":1,"v":{"a":0,"k":[0,0,0.23921568627450981,1],"ix":1}}]}],"ip":0,"op":101,"st":0,"bm":0},{"ddd":0,"ind":8,"ty":3,"nm":"","sr":1,"ks":{"p":{"a":0,"k":[249.99998474121094,250],"ix":2},"a":{"a":0,"k":[125.76160049438477,153.60006713867188],"ix":2},"s":{"a":0,"k":[130.0251007080078,130.0251007080078],"ix":2},"r":{"a":0,"k":0,"ix":2},"o":{"a":0,"k":100,"ix":2},"sk":{"a":0,"k":0,"ix":2},"sa":{"a":0,"k":0,"ix":2}},"ao":0,"ip":0,"op":101,"st":0,"bm":0},{"ddd":0,"refId":"1","w":308,"h":308,"ind":7,"ty":0,"nm":"SVG","sr":1,"ks":{"p":{"a":0,"k":[-28,0],"ix":2},"a":{"a":0,"k":[0,0],"ix":2},"s":{"a":0,"k":[100,100],"ix":2},"r":{"a":0,"k":0,"ix":2},"o":{"a":0,"k":100,"ix":2},"sk":{"a":0,"k":0,"ix":2},"sa":{"a":0,"k":0,"ix":2}},"ao":0,"ip":0,"op":101,"st":0,"bm":0,"parent":8}],"markers":[]}